immanuel_verted/__init__.py
immanuel_verted/charts.py
immanuel_verted/setup.py
immanuel_verted/locales/es_ES/LC_MESSAGES/immanuel.mo
immanuel_verted/locales/pt_BR/LC_MESSAGES/immanuel.mo
immanuel_verted/resources/ephemeris/seas_12.se1
immanuel_verted/resources/ephemeris/seas_18.se1
immanuel_verted/resources/ephemeris/seas_24.se1
immanuel_verted/resources/ephemeris/semo_12.se1
immanuel_verted/resources/ephemeris/semo_18.se1
immanuel_verted/resources/ephemeris/semo_24.se1
immanuel_verted/resources/ephemeris/semo_36.se1
immanuel_verted/resources/ephemeris/semo_42.se1
immanuel_verted/resources/ephemeris/sepl_12.se1
immanuel_verted/resources/ephemeris/sepl_18.se1
immanuel_verted/resources/ephemeris/sepl_24.se1
immanuel_verted/resources/ephemeris/sepl_36.se1
immanuel_verted/resources/ephemeris/sepl_42.se1
immanuel_verted-0.1.2.dist-info/LICENSE.md
immanuel_verted-0.1.2.dist-info/METADATA
immanuel_verted-0.1.2.dist-info/WHEEL
immanuel_verted-0.1.2.dist-info/top_level.txt
immanuel_verted-0.1.2.dist-info/RECORD
