Metadata-Version: 2.1
Name: immanuel_verted
Version: 0.1.2
Summary: Quickly produce both human-readable and JSON-formatted astrology chart data based on the Swiss Ephemeris and astro.com.
Home-page: https://github.com/EthanAbra/immanuel-verted
Author: Your Name
Author-email: Robert Davies <robert@theriftlab.com>
License: # GNU AFFERO GENERAL PUBLIC LICENSE
Project-URL: Homepage, https://github.com/theriftlab/immanuel-python
Project-URL: Documentation, https://github.com/theriftlab/immanuel-python/blob/master/docs/1-overview.md
Project-URL: Bug Tracker, https://github.com/theriftlab/immanuel-python/issues
Keywords: astrology,api,pyswisseph,swisseph,swiss ephemeris,astro.com,astro gold
Classifier: Programming Language :: Python :: 3
Classifier: License :: OSI Approved :: GNU General Public License v3 or later (GPLv3+)
Classifier: Operating System :: OS Independent
Requires-Python: >=3.8
License-File: LICENSE.md
Requires-Dist: pyswisseph ~=2.10
Requires-Dist: python-dateutil
Requires-Dist: timezonefinder ~=5.2
Requires-Dist: pytest
Provides-Extra: dev
Requires-Dist: pytest >=6.0 ; extra == 'dev'
Requires-Dist: pytest-cov >=2.0 ; extra == 'dev'
Requires-Dist: black ; extra == 'dev'
Requires-Dist: flake8 ; extra == 'dev'
Requires-Dist: mypy ; extra == 'dev'
Requires-Dist: twine ; extra == 'dev'
Requires-Dist: wheel ; extra == 'dev'
